bardapi/__init__.py
bardapi/core.py
googlebardapi-0.1.2.dist-info/LICENSE
googlebardapi-0.1.2.dist-info/METADATA
googlebardapi-0.1.2.dist-info/WHEEL
googlebardapi-0.1.2.dist-info/top_level.txt
googlebardapi-0.1.2.dist-info/RECORD
